{
  "parent": "minecraft:recipes/root",
  "rewards": {
    "recipes": [
      "excavator:excavator_minecart"
    ]
  },
  "criteria": {
    "has_items": {
      "trigger": "minecraft:inventory_changed",
      "conditions": {
        "items": [
          {
            "item": "minecraft:minecart"
          },
          {
            "item": "minecraft:redstone_block"
          },
          {
            "item": "minecraft:observer"
          },
          {
            "item": "minecraft:hopper"
          }
        ]
      }
    },
    "has_the_recipe": {
      "trigger": "minecraft:recipe_unlocked",
      "conditions": {
        "recipe": "excavator:excavator_minecart"
      }
    }
  },
  "requirements": [
    [
      "has_items",
      "has_the_recipe"
    ]
  ]
}